escape/__init__.py
escape/main.py
escape/room.py
escape/state.py
escape/img/chest.png
escape/img/chest_opened.png
escape/img/door.png
escape/img/keypad.png
escape/img/light_switch_off.png
escape/img/light_switch_on.png
escape/img/math.png
escape/img/maxi_window.png
escape/img/mini_chest.png
escape/img/mini_chest_opened.png
escape/img/mini_light_switch_off.png
escape/img/mini_light_switch_on.png
escape/img/mini_math.png
escape/img/mini_window.png
escape/img/mini_zodiac.png
escape/img/window.png
escape/img/zodiac.png
kitty_escape-1.3.2.dist-info/licenses/LICENSE
kitty_escape-1.3.2.dist-info/METADATA
kitty_escape-1.3.2.dist-info/WHEEL
kitty_escape-1.3.2.dist-info/entry_points.txt
kitty_escape-1.3.2.dist-info/top_level.txt
kitty_escape-1.3.2.dist-info/RECORD
