Metadata-Version: 2.4
Name: kitty-escape
Version: 1.3.2
Summary: kitty escape game
Home-page: https://github.com/rchen152/escape
Classifier: Programming Language :: Python :: 3
Classifier: License :: OSI Approved :: GNU General Public License v3 (GPLv3)
Classifier: Operating System :: POSIX :: Linux
Requires-Python: >=3.10
License-File: LICENSE
Requires-Dist: kitty-common>=0.5.5
Requires-Dist: pygame>=2.1.2
Dynamic: classifier
Dynamic: description
Dynamic: description-content-type
Dynamic: home-page
Dynamic: license-file
Dynamic: requires-dist
Dynamic: requires-python
Dynamic: summary
